[
  {
    "id": "gear-yhfxc2",
    "name": "Pro Training Cone Set",
    "description": "Durable cones for agility drills.",
    "sport": "baseball",
    "category": "training",
    "brand": "AgiliPro",
    "model": "AP-200",
    "price": 24.99,
    "currency": "USD",
    "imageUrl": "https://picsum.photos/seed/gear/400/300",
    "creatorUid": "uid_creator_soccer_1",
    "creatorName": "Cameron",
    "purchaseUrl": "https://example.com/gear/cones",
    "affiliateUrl": "https://aff.example.com/gear/cones",
    "isActive": true,
    "isRecommended": true,
    "createdAt": "2025-07-30T19:21:33.401513+00:00",
    "updatedAt": "2025-09-15T19:21:33.401513+00:00"
  },
  {
    "id": "gear-rwzt0c",
    "name": "Pro Training Cone Set",
    "description": "Durable cones for agility drills.",
    "sport": "soccer",
    "category": "training",
    "brand": "AgiliPro",
    "model": "AP-200",
    "price": 24.99,
    "currency": "USD",
    "imageUrl": "https://picsum.photos/seed/gear/400/300",
    "creatorUid": "uid_creator_soccer_2",
    "creatorName": "Taylor",
    "purchaseUrl": "https://example.com/gear/cones",
    "affiliateUrl": "https://aff.example.com/gear/cones",
    "isActive": true,
    "isRecommended": true,
    "createdAt": "2025-07-30T19:21:33.401513+00:00",
    "updatedAt": "2025-09-15T19:21:33.401513+00:00"
  },
  {
    "id": "gear-622s9y",
    "name": "Pro Training Cone Set",
    "description": "Durable cones for agility drills.",
    "sport": "soccer",
    "category": "training",
    "brand": "AgiliPro",
    "model": "AP-200",
    "price": 24.99,
    "currency": "USD",
    "imageUrl": "https://picsum.photos/seed/gear/400/300",
    "creatorUid": "uid_creator_soccer_3",
    "creatorName": "Taylor",
    "purchaseUrl": "https://example.com/gear/cones",
    "affiliateUrl": "https://aff.example.com/gear/cones",
    "isActive": true,
    "isRecommended": true,
    "createdAt": "2025-07-30T19:21:33.401513+00:00",
    "updatedAt": "2025-09-15T19:21:33.401513+00:00"
  },
  {
    "id": "gear-zxxa15",
    "name": "Pro Training Cone Set",
    "description": "Durable cones for agility drills.",
    "sport": "running",
    "category": "training",
    "brand": "AgiliPro",
    "model": "AP-200",
    "price": 24.99,
    "currency": "USD",
    "imageUrl": "https://picsum.photos/seed/gear/400/300",
    "creatorUid": "uid_creator_basketball_1",
    "creatorName": "Cameron",
    "purchaseUrl": "https://example.com/gear/cones",
    "affiliateUrl": "https://aff.example.com/gear/cones",
    "isActive": true,
    "isRecommended": true,
    "createdAt": "2025-07-30T19:21:33.401513+00:00",
    "updatedAt": "2025-09-15T19:21:33.401513+00:00"
  },
  {
    "id": "gear-jgovhq",
    "name": "Pro Training Cone Set",
    "description": "Durable cones for agility drills.",
    "sport": "football",
    "category": "training",
    "brand": "AgiliPro",
    "model": "AP-200",
    "price": 24.99,
    "currency": "USD",
    "imageUrl": "https://picsum.photos/seed/gear/400/300",
    "creatorUid": "uid_creator_basketball_2",
    "creatorName": "Parker",
    "purchaseUrl": "https://example.com/gear/cones",
    "affiliateUrl": "https://aff.example.com/gear/cones",
    "isActive": true,
    "isRecommended": true,
    "createdAt": "2025-07-30T19:21:33.401513+00:00",
    "updatedAt": "2025-09-15T19:21:33.401513+00:00"
  },
  {
    "id": "gear-eqs44p",
    "name": "Pro Training Cone Set",
    "description": "Durable cones for agility drills.",
    "sport": "football",
    "category": "training",
    "brand": "AgiliPro",
    "model": "AP-200",
    "price": 24.99,
    "currency": "USD",
    "imageUrl": "https://picsum.photos/seed/gear/400/300",
    "creatorUid": "uid_creator_basketball_3",
    "creatorName": "Taylor",
    "purchaseUrl": "https://example.com/gear/cones",
    "affiliateUrl": "https://aff.example.com/gear/cones",
    "isActive": true,
    "isRecommended": true,
    "createdAt": "2025-07-30T19:21:33.401513+00:00",
    "updatedAt": "2025-09-15T19:21:33.401513+00:00"
  },
  {
    "id": "gear-2zzl2e",
    "name": "Pro Training Cone Set",
    "description": "Durable cones for agility drills.",
    "sport": "basketball",
    "category": "training",
    "brand": "AgiliPro",
    "model": "AP-200",
    "price": 24.99,
    "currency": "USD",
    "imageUrl": "https://picsum.photos/seed/gear/400/300",
    "creatorUid": "uid_creator_baseball_1",
    "creatorName": "Sydney",
    "purchaseUrl": "https://example.com/gear/cones",
    "affiliateUrl": "https://aff.example.com/gear/cones",
    "isActive": true,
    "isRecommended": true,
    "createdAt": "2025-07-30T19:21:33.401513+00:00",
    "updatedAt": "2025-09-15T19:21:33.401513+00:00"
  },
  {
    "id": "gear-eitvjp",
    "name": "Pro Training Cone Set",
    "description": "Durable cones for agility drills.",
    "sport": "bjj",
    "category": "training",
    "brand": "AgiliPro",
    "model": "AP-200",
    "price": 24.99,
    "currency": "USD",
    "imageUrl": "https://picsum.photos/seed/gear/400/300",
    "creatorUid": "uid_creator_baseball_2",
    "creatorName": "Morgan",
    "purchaseUrl": "https://example.com/gear/cones",
    "affiliateUrl": "https://aff.example.com/gear/cones",
    "isActive": true,
    "isRecommended": true,
    "createdAt": "2025-07-30T19:21:33.401513+00:00",
    "updatedAt": "2025-09-15T19:21:33.401513+00:00"
  },
  {
    "id": "gear-cheg42",
    "name": "Pro Training Cone Set",
    "description": "Durable cones for agility drills.",
    "sport": "track",
    "category": "training",
    "brand": "AgiliPro",
    "model": "AP-200",
    "price": 24.99,
    "currency": "USD",
    "imageUrl": "https://picsum.photos/seed/gear/400/300",
    "creatorUid": "uid_creator_baseball_3",
    "creatorName": "Riley",
    "purchaseUrl": "https://example.com/gear/cones",
    "affiliateUrl": "https://aff.example.com/gear/cones",
    "isActive": true,
    "isRecommended": true,
    "createdAt": "2025-07-30T19:21:33.401513+00:00",
    "updatedAt": "2025-09-15T19:21:33.401513+00:00"
  },
  {
    "id": "gear-0fk4lc",
    "name": "Pro Training Cone Set",
    "description": "Durable cones for agility drills.",
    "sport": "golf",
    "category": "training",
    "brand": "AgiliPro",
    "model": "AP-200",
    "price": 24.99,
    "currency": "USD",
    "imageUrl": "https://picsum.photos/seed/gear/400/300",
    "creatorUid": "uid_creator_tennis_1",
    "creatorName": "Parker",
    "purchaseUrl": "https://example.com/gear/cones",
    "affiliateUrl": "https://aff.example.com/gear/cones",
    "isActive": true,
    "isRecommended": true,
    "createdAt": "2025-07-30T19:21:33.401513+00:00",
    "updatedAt": "2025-09-15T19:21:33.401513+00:00"
  }
]